helloworld.py
aks_helloworld-0.0.1.dist-info/LICENSE.txt
aks_helloworld-0.0.1.dist-info/METADATA
aks_helloworld-0.0.1.dist-info/WHEEL
aks_helloworld-0.0.1.dist-info/top_level.txt
aks_helloworld-0.0.1.dist-info/RECORD
